{
  "generated_at": "2026-07-02T10:24:22.767Z",
  "meta": {
    "parent_file": "scrapester.json",
    "price_max_exclusive": 1000,
    "geo_circle": {
      "center": {
        "lat": 30.4983,
        "lon": -86.1361
      },
      "radius_miles": 300
    },
    "counts": {
      "exported_ads": 52,
      "droppedPrice": 615,
      "droppedMissingGeo": 0,
      "droppedCircle": 657
    }
  },
  "ads": [
    {
      "adID": "1522248433022473",
      "source": "MP",
      "authorUrl": "https://www.facebook.com/marketplace/profile/61558933102738/?product_id=1522248433022473",
      "author": "Walt Greg Chastain",
      "postedTime": "2026-07-02T00:38:04.000Z",
      "title": "I play Arcade machine. 800 OBO",
      "description": "Like-New iPlay Retro Arcade Machine (Model IPRET09) – Perfect Condition!Price: $800 Condition: Used – Like New Selling a beautiful iPlay Retro Arcade Game Machine (Model: IPRET09) in flawless, 100% perfect working condition. There are absolutely no cosmetic flaws, scratches, or mechanical issues with the joysticks, buttons, or screen.We absolutely love this machine, but we are moving soon and simply do not have the floor room for it in our next place. It has been meticulously cared for in a smoke-free home.Key Features & Details:Model Number: IPRET09Condition: Perfect, like-new condition (fully tested and working)Design: Authentic retro cabinet style with crisp display and responsive controlsGames: Pre-loaded with classic arcade favorites—plug in and play immediately!Pickup & Payment Details:Price: $800 cash or secure electronic payment upon pickupLocation: Local pickup only (Bring a vehicle large enough to transport)",
      "price": "$800",
      "lat": 27.871197,
      "lon": -82.3269883,
      "location": "Riverview, FL",
      "imageUrl": "https://scontent-dfw6-2.xx.fbcdn.net/v/t15.5256-10/733849660_869331099580812_447496107329785420_n.jpg?stp=dst-jpg_tt6&cstp=mx720x1280&ctp=s960x960&_nc_cat=109&ccb=1-7&_nc_sid=d4195b&_nc_ohc=pDVtXBPR_1MQ7kNvwF5gV56&_nc_oc=Adr_aTgRfDlTXrw6jX39PI3Adv36CKhgcRPFdlJZ2LJCZ2He3F1HKaozduWVmVj2xMI&_nc_zt=23&_nc_ht=scontent-dfw6-2.xx&_nc_gid=0sbULY5DNJK62kD-N9km8Q&_nc_ss=7b2a8&oh=00_AQDo-rIxe9DOj-B14eTvhiS_KB54ZpJtwrm7r-88n9DBug&oe=6A4B7F2F",
      "adUrl": "https://www.facebook.com/marketplace/item/1522248433022473/",
      "priceChanged": 0,
      "priceChangedAt": null,
      "hidden": 0,
      "created_at": "2026-07-02 01:12:18",
      "lastSeen": "2026-07-02T01:15:26.922Z"
    },
    {
      "adID": "KLOV-564279",
      "source": "KLOV",
      "authorUrl": "https://forums.arcade-museum.com/members/digindug82.83438/",
      "author": "Digindug82",
      "postedTime": "2026-07-01T22:40:18.000Z",
      "title": "Centipede cocktail harness",
      "description": "I found another Centipede cocktail harness, this one has the correct power plug for the transformer assembly all connectors are intact no wires cut, the slam switch wires came undone (slam switch included) the monitor connection is not included $125.00 shipped in the USA",
      "price": "$125",
      "lat": 28.5551912,
      "lon": -81.7669488,
      "location": "Clermont, Florida",
      "imageUrl": "/images/klov-placeholder.png",
      "adUrl": "https://forums.arcade-museum.com/threads/564279/",
      "priceChanged": 0,
      "priceChangedAt": null,
      "hidden": 0,
      "created_at": "2026-07-01 23:18:59",
      "lastSeen": "2026-07-02T01:19:35.392Z"
    },
    {
      "adID": "2594159494372390",
      "source": "MP",
      "authorUrl": "https://www.facebook.com/marketplace/profile/500398628/?product_id=2594159494372390",
      "author": "Evans Martin",
      "postedTime": "2026-07-01T22:32:08.000Z",
      "title": "Golden Tee 3D Arcade Video Game",
      "description": "This is a full size Golden Tee 3D Arcade Game, like the one you remember from the bars in the late 90’s, early 2000’s. It has been converted to a LCD monitor for reliability and works 100%. It even has a working dollar bill acceptor if you want to charge your friends to play lol. $500 Located in Tyrone, GA 30290",
      "price": "$500",
      "lat": 33.4713249,
      "lon": -84.5972005,
      "location": "Tyrone, GA",
      "imageUrl": "https://scontent-dfw6-2.xx.fbcdn.net/v/t15.5256-10/736878008_2201975830345660_6257556788046792351_n.jpg?stp=dst-jpg_tt6&cstp=mx1280x720&ctp=s960x960&_nc_cat=108&ccb=1-7&_nc_sid=d4195b&_nc_ohc=2XqQEIB2bfoQ7kNvwEVa9Pz&_nc_oc=AdpGn-pG4l_QSZe0HB4XiDCmPdeQu2tkayzxXzTbrySrusXVcGrRGfpPE_QgFH49NEI&_nc_zt=23&_nc_ht=scontent-dfw6-2.xx&_nc_gid=OujfrdAqjfR61OImymTAyg&_nc_ss=7b2a8&oh=00_AQBwqx9pENdGz1YQRgL7hQsY9XikyhHaSPuvRlu9BGOZgg&oe=6A4B88DD",
      "adUrl": "https://www.facebook.com/marketplace/item/2594159494372390/",
      "priceChanged": 0,
      "priceChangedAt": null,
      "hidden": 0,
      "created_at": "2026-07-01 23:12:21",
      "lastSeen": "2026-07-02T01:12:18.026Z"
    },
    {
      "adID": "1504673857495048",
      "source": "MP",
      "authorUrl": "https://www.facebook.com/marketplace/profile/100001339612288/?product_id=1504673857495048",
      "author": "Paul Xander Joy",
      "postedTime": "2026-07-01T21:02:06.000Z",
      "title": "Nintendo games",
      "description": "Nintendo games Airwolf Double dragon Spyhunter Qbert Pinball Tetris Hoops Goal Rbi baseball Indiana Jones temple of doom",
      "price": "$100",
      "lat": 29.9060388,
      "lon": -90.1422962,
      "location": "Westwego, LA",
      "imageUrl": "https://scontent-dfw6-2.xx.fbcdn.net/v/t39.84726-6/735608318_1357514266286751_2477849284801805076_n.jpg?stp=dst-jpg_p720x720_tt6&_nc_cat=109&ccb=1-7&_nc_sid=92e707&_nc_ohc=t5_vTGDPAEcQ7kNvwF1Hs16&_nc_oc=AdrOPzNo-nj90goJeJgZqCN-ygNXzQb-giPAdzj8ZRr9u5NemPGp9pWPywO_rMqCOhU&_nc_zt=14&_nc_ht=scontent-dfw6-2.xx&_nc_gid=4Ej3bqpmvmsCLabR8VvO6w&_nc_ss=7b2a8&oh=00_AQAKH1OB8DMNA-pcPZwkvqBQIjuJ2azPfoLDqqLfACM8DA&oe=6A4B3A63",
      "adUrl": "https://www.facebook.com/marketplace/item/1504673857495048/",
      "priceChanged": 0,
      "priceChangedAt": null,
      "hidden": 0,
      "created_at": "2026-07-01 21:15:38",
      "lastSeen": "2026-07-02T01:15:25.985Z"
    },
    {
      "adID": "797775553325163",
      "source": "MP",
      "authorUrl": "https://www.facebook.com/marketplace/profile/61588554120093/?product_id=797775553325163",
      "author": "Tampa Bae",
      "postedTime": "2026-07-01T05:38:51.000Z",
      "title": "Metal Film Reels",
      "description": "Decorative. Three film reels are included, two silver and one black. A silver film strip is also included. Metal",
      "price": "$15",
      "lat": 27.9449854,
      "lon": -82.4583107,
      "location": "Tampa, FL",
      "imageUrl": "https://scontent-dfw6-1.xx.fbcdn.net/v/t39.84726-6/734705995_4286716458245606_250304017444682834_n.jpg?stp=dst-jpg_s960x960_tt6&_nc_cat=103&ccb=1-7&_nc_sid=92e707&_nc_ohc=37I-_avGCRMQ7kNvwGmBFlI&_nc_oc=AdolQrwcRImuQRCZyJZKBi96AzYR5L9uh4okNiIOMAoUdXY5VZZcyOXGvXrUhnLlmZQ&_nc_zt=14&_nc_ht=scontent-dfw6-1.xx&_nc_gid=RQfo5VuHHVl3t_KB6Toksw&_nc_ss=7b2a8&oh=00_AQB3zBeqSY47iT2RKrSo2UGFc_XCnPaJmcVY1CP_HcUpdQ&oe=6A4B5872",
      "adUrl": "https://www.facebook.com/marketplace/item/797775553325163/",
      "priceChanged": 0,
      "priceChangedAt": null,
      "hidden": 0,
      "created_at": "2026-07-01 20:15:56",
      "lastSeen": "2026-07-01T20:22:41.122Z"
    },
    {
      "adID": "2392027531285373",
      "source": "MP",
      "authorUrl": "https://www.facebook.com/marketplace/profile/100089636895277/?product_id=2392027531285373",
      "author": "Gerald Hauber",
      "postedTime": "2026-07-01T15:55:03.000Z",
      "title": "Vintage Jocko Bagatelle Pinball Game",
      "description": "Vintage Jocko Bagatelle Pinball Game – Wolverine Toy, Booneville Arkansas, no fading on lithograph game surface, all balls (3 white, 1 black), spring loaded plunger fully functional, plastic cover very minimal yellowing, no cracks front-side, no tears backside, 12-1/2 inch height, non-smoking home. Cash Only, Public Pickup (Lakewood Ranch Starbucks at 7224 University Parkway just east of Lorraine Road, next to Aldis’s) Thank you",
      "price": "$19",
      "lat": 27.4989278,
      "lon": -82.5748194,
      "location": "Bradenton, FL",
      "imageUrl": "https://scontent-dfw6-1.xx.fbcdn.net/v/t39.84726-6/736226330_983989357955795_8720186089895441728_n.jpg?stp=dst-jpg_s960x960_tt6&_nc_cat=102&ccb=1-7&_nc_sid=92e707&_nc_ohc=RTi3L0G14qsQ7kNvwH4ZQ72&_nc_oc=AdoW_OgGSrSxpRJyxwDP6B8QtKIydxwYAEx5Y4ghU5X7TLIDAheIf-J5v9xrAgI1xds&_nc_zt=14&_nc_ht=scontent-dfw6-1.xx&_nc_gid=GQ2ASJAYc3dAMAu-M68t6w&_nc_ss=7b2a8&oh=00_AQAvMng2Xclrqu4B3EEv88A_uH8x6oEAFZamszwf24NnAw&oe=6A4B170F",
      "adUrl": "https://www.facebook.com/marketplace/item/2392027531285373/",
      "priceChanged": 0,
      "priceChangedAt": null,
      "hidden": 0,
      "created_at": "2026-07-01 16:34:48",
      "lastSeen": "2026-07-02T01:15:26.153Z"
    },
    {
      "adID": "1974728540076397",
      "source": "MP",
      "authorUrl": "https://www.facebook.com/marketplace/profile/100019583682534/?product_id=1974728540076397",
      "author": "Stephanie Bise",
      "postedTime": "2026-07-01T05:38:38.000Z",
      "title": "Steering Wheel Game Console",
      "description": "steering wheel gaming console. hooks up to any system. my son just don’t play it anymore. the new wore off.",
      "price": "$60",
      "lat": 34.0128323,
      "lon": -86.0030251,
      "location": "Gadsden, AL",
      "imageUrl": "https://scontent-dfw5-1.xx.fbcdn.net/v/t39.84726-6/736440458_1930166947692576_8062471522963263818_n.jpg?stp=dst-jpg_s960x960_tt6&_nc_cat=111&ccb=1-7&_nc_sid=92e707&_nc_ohc=6yNmxbIgbSEQ7kNvwGI65Xj&_nc_oc=AdrckH7_2L2tzUNZ5Esft63auUZjVp7NU--BxnQvxPvw55HZwHseoIA2lWxvmYJntFc&_nc_zt=14&_nc_ht=scontent-dfw5-1.xx&_nc_gid=m3SvcUIibeg8CAggQRkGvw&_nc_ss=7b2a8&oh=00_AQAdQ3ilLtKNyNh8K3Mu5U0XpwUFTQSzlxPLUmf0O0eJGQ&oe=6A4B209D",
      "adUrl": "https://www.facebook.com/marketplace/item/1974728540076397/",
      "priceChanged": 0,
      "priceChangedAt": null,
      "hidden": 0,
      "created_at": "2026-07-01 16:12:23",
      "lastSeen": "2026-07-02T01:12:18.260Z"
    },
    {
      "adID": "KLOV-475680",
      "source": "KLOV",
      "authorUrl": "https://forums.arcade-museum.com/members/kittybeater.35366/",
      "author": "kittybeater",
      "postedTime": "2026-07-01T14:56:53.000Z",
      "title": "Sega / Subroc 3D Lighted Crosshair Assembly $59.99",
      "description": "Sega / Subroc 3D Lighted Crosshair Assembly $59.99 picture on this page Misc Other Game Parts Arcade Game Parts, Space Invaders Deluxe Moon Backdrop, Space Encounter Monitor Overlay, Slick Shot Ball Returns, Xico Card Reader thearcadeboneyard.com [email protected]",
      "price": "$59",
      "lat": 29.1871986,
      "lon": -82.1400923,
      "location": "Ocala, Florida",
      "imageUrl": "/images/klov-placeholder.png",
      "adUrl": "https://forums.arcade-museum.com/threads/475680/",
      "priceChanged": 0,
      "priceChangedAt": null,
      "hidden": 0,
      "created_at": "2026-07-01 15:23:07",
      "lastSeen": "2026-07-02T01:19:35.849Z"
    },
    {
      "adID": "1685994949344486",
      "source": "MP",
      "authorUrl": "https://www.facebook.com/marketplace/profile/1734624958/?product_id=1685994949344486",
      "author": "Lori King",
      "postedTime": "2026-07-01T14:29:43.000Z",
      "title": "Pac-Man Game",
      "description": "",
      "price": "$200",
      "lat": 32.4490141,
      "lon": -81.7832912,
      "location": "Statesboro, GA",
      "imageUrl": "https://scontent-dfw6-2.xx.fbcdn.net/v/t39.84726-6/733737956_1536262864859921_1051267109984145979_n.jpg?stp=dst-jpg_s960x960_tt6&_nc_cat=110&ccb=1-7&_nc_sid=92e707&_nc_ohc=KA9tF9wZYWIQ7kNvwEcuMuE&_nc_oc=AdrrdgTvnWH09IpZssgTV1shSbKDja9--4PpZFDgTvfoSaoPmSqkgQt9NIb4KnNToV8&_nc_zt=14&_nc_ht=scontent-dfw6-2.xx&_nc_gid=P0TaCChWxIjCzT03MmPQEA&_nc_ss=7b2a8&oh=00_AQDwmku-0ynvG5g-J7MF2LXwxzJckxCZBn89uEZE7-cdkw&oe=6A4B0703",
      "adUrl": "https://www.facebook.com/marketplace/item/1685994949344486/",
      "priceChanged": 0,
      "priceChangedAt": null,
      "hidden": 0,
      "created_at": "2026-07-01 15:14:53",
      "lastSeen": "2026-07-02T01:15:27.359Z"
    },
    {
      "adID": "1317784970549944",
      "source": "MP",
      "authorUrl": "https://www.facebook.com/marketplace/profile/1548015469/?product_id=1317784970549944",
      "author": "Tara Werho",
      "postedTime": "2026-07-01T14:59:07.000Z",
      "title": "Vintage Coin-Operated Pinball Bagatelle Machine",
      "description": "Vintage coin-operated pinball machine has a wooden cabinet with a black finish and a glass-covered playfield. This bagatelle-style game includes four detachable wooden legs with metal levelers. The playfield features metal pins, scoring cups, and a spring-loaded plunger mechanism. A coin slot is located on the front panel.",
      "price": "$450",
      "lat": 33.5215013,
      "lon": -84.3538128,
      "location": "Jonesboro, GA",
      "imageUrl": "https://scontent-dfw6-1.xx.fbcdn.net/v/t39.84726-6/736218212_1929393714386253_5290954874831474128_n.jpg?stp=dst-jpg_s960x960_tt6&_nc_cat=101&ccb=1-7&_nc_sid=92e707&_nc_ohc=3QydGf7cz_8Q7kNvwHY1ivY&_nc_oc=AdqgUCQkeZlwDHNcoJQqFzrH0WwG2Qc9mcKzokIS7el9sSh67zFYAv_b5mWu-oETxpY&_nc_zt=14&_nc_ht=scontent-dfw6-1.xx&_nc_gid=IQlqWldtxL_knjVnfFn6lA&_nc_ss=7b2a8&oh=00_AQD_4a8XDD8bewkrXdQiDZnG63AuF6nhjAC3ks2GzLM2-g&oe=6A4AEA10",
      "adUrl": "https://www.facebook.com/marketplace/item/1317784970549944/",
      "priceChanged": 0,
      "priceChangedAt": null,
      "hidden": 0,
      "created_at": "2026-07-01 15:14:51",
      "lastSeen": "2026-07-02T01:15:26.219Z"
    },
    {
      "adID": "2123675245216404",
      "source": "MP",
      "authorUrl": "https://www.facebook.com/marketplace/profile/837574389/?product_id=2123675245216404",
      "author": "Dirk Smith Johnson",
      "postedTime": "2026-07-01T14:46:14.000Z",
      "title": "Pinball and arcade ganes",
      "description": "Are you looking for pinball and arcade games? Look at our selection at the broad theater 636 North Broad. Variety of selections and inquire for prices and availability. Open daily from about 11:00 a.m. to 10:00 p.m.. Come play!",
      "price": "$1",
      "lat": 30.0018547,
      "lon": -90.1767012,
      "location": "Metairie, LA",
      "imageUrl": "https://scontent-dfw5-2.xx.fbcdn.net/v/t39.84726-6/735010003_1050946603934354_6867384359656454004_n.jpg?stp=dst-jpg_s960x960_tt6&_nc_cat=100&ccb=1-7&_nc_sid=92e707&_nc_ohc=1LGGg7O4MJQQ7kNvwE4Y63N&_nc_oc=Adqi8GpQczFn7fJrG4WjpYYIExVeHwIL5Yj-M9CvvIkds-JtVpQiqO6VhpT2Ls1jjgs&_nc_zt=14&_nc_ht=scontent-dfw5-2.xx&_nc_gid=pLBP4HWWygOxb8HvYBwUSQ&_nc_ss=7b2a8&oh=00_AQCOFLiTAQEQxjk16L8StCCbj4ZyduFk-P238K5aqGcCeA&oe=6A4B018D",
      "adUrl": "https://www.facebook.com/marketplace/item/2123675245216404/",
      "priceChanged": 0,
      "priceChangedAt": null,
      "hidden": 0,
      "created_at": "2026-07-01 15:12:08",
      "lastSeen": "2026-07-02T01:15:26.253Z"
    },
    {
      "adID": "1730224717972003",
      "source": "MP",
      "authorUrl": "https://www.facebook.com/marketplace/profile/100092856637233/?product_id=1730224717972003",
      "author": "Sean Allen",
      "postedTime": "2026-06-30T18:21:27.000Z",
      "title": "Golden tee golf arcade video game",
      "description": "I have a golden tee golf arcade video game, works just like it should. Has on/ off switch and volume control. $150. Must pick up west Pensacola area.",
      "price": "$150",
      "lat": 30.421309,
      "lon": -87.2169149,
      "location": "Pensacola, FL",
      "imageUrl": "https://scontent-dfw6-1.xx.fbcdn.net/v/t15.5256-10/735058410_899204532496201_683699921130036987_n.jpg?stp=dst-jpg_tt6&cstp=mx720x1280&ctp=s960x960&_nc_cat=103&ccb=1-7&_nc_sid=d4195b&_nc_ohc=Bpm1TQhmt_0Q7kNvwFmwD5s&_nc_oc=AdpVRJnPeQy_hvkDVcZBt4AvKfJbLTaBF2jhPlRRG7J_H0CAttU_DWZ5bcdX5t0pCbA&_nc_zt=23&_nc_ht=scontent-dfw6-1.xx&_nc_gid=DSlFQGo2a4JDT8VqpaScmA&_nc_ss=7b2a8&oh=00_AQCtf31JfCepl_y_XJcTnsOSK6jH9opu4FCYl3RLdS0hPQ&oe=6A49DE09",
      "adUrl": "https://www.facebook.com/marketplace/item/1730224717972003/",
      "priceChanged": 0,
      "priceChangedAt": null,
      "hidden": 0,
      "created_at": "2026-06-30 19:12:08",
      "lastSeen": "2026-06-30T22:11:56.873Z"
    },
    {
      "adID": "1464323905381196",
      "source": "MP",
      "authorUrl": "https://www.facebook.com/marketplace/profile/61582269337504/?product_id=1464323905381196",
      "author": "Janique Fowlin",
      "postedTime": "2026-06-30T18:02:53.000Z",
      "title": "Valley Cougar Darts Arcade Machine – Project / Parts",
      "description": "Vintage Valley Cougar Darts electronic arcade machine. Cabinet is in good overall condition for its age. The machine powers on, but only about half of the dartboard registers hits. It needs a sensor repair/replacement to be fully functional. Scoreboard, cabinet, and electronics appear to be intact, making it a great project for someone familiar with arcade machines or looking for parts. Delivery available for a fee",
      "price": "$250",
      "lat": 27.7712264,
      "lon": -82.6340259,
      "location": "St Petersburg, FL",
      "imageUrl": "https://scontent-dfw6-1.xx.fbcdn.net/v/t39.84726-6/732933788_1033513235733347_811580999000248870_n.jpg?stp=dst-jpg_p720x720_tt6&_nc_cat=101&ccb=1-7&_nc_sid=92e707&_nc_ohc=mLSR5oUCEPMQ7kNvwGp5a13&_nc_oc=Adr6RmT9oh8FGwD84hlHLUMlxYP-0TVDKpRWaXyB1IRtnMXVZhCl4YTPxzPmE10yNn8&_nc_zt=14&_nc_ht=scontent-dfw6-1.xx&_nc_gid=nl5GDR9RG4VJfHmOcMtJ-A&_nc_ss=7b2a8&oh=00_AQB_Srftuaa9UI7Ix2_dF5XFgyuqOKpEvAQjZH81PpeCdw&oe=6A49EB2E",
      "adUrl": "https://www.facebook.com/marketplace/item/1464323905381196/",
      "priceChanged": 0,
      "priceChangedAt": null,
      "hidden": 0,
      "created_at": "2026-06-30 18:12:05",
      "lastSeen": "2026-07-02T01:12:18.662Z"
    },
    {
      "adID": "2077568293133611",
      "source": "MP",
      "authorUrl": "https://www.facebook.com/marketplace/profile/1053682551/?product_id=2077568293133611",
      "author": "Kitty Loyer Burga",
      "postedTime": "2026-06-30T17:54:37.000Z",
      "title": "Bill Acceptor DOOR for Arcade Game, no bill acceptor, just straight door with lock & 2 keys",
      "description": "Only door",
      "price": "$20",
      "lat": 33.9597677,
      "lon": -83.376398,
      "location": "Athens, GA",
      "imageUrl": "https://scontent-dfw6-2.xx.fbcdn.net/v/t39.84726-6/734756349_3876473255994958_8142148479124231279_n.jpg?stp=dst-jpg_s960x960_tt6&_nc_cat=110&ccb=1-7&_nc_sid=92e707&_nc_ohc=I1LSr0uuoV4Q7kNvwF_5Ws0&_nc_oc=AdqG6zeN07OSZYh-5azX5G3Rl6kaVZigDn5POoTP-msipmAebF6hMnofFodozQyHJ8s&_nc_zt=14&_nc_ht=scontent-dfw6-2.xx&_nc_gid=EwePjpvXSxFNhwe1c0UdSQ&_nc_ss=7b2a8&oh=00_AQDJHa6jF_rcN8DXaZWdKYn0MsO_fwAmY4lhOgiMb2uwoA&oe=6A49D73E",
      "adUrl": "https://www.facebook.com/marketplace/item/2077568293133611/",
      "priceChanged": 0,
      "priceChangedAt": null,
      "hidden": 0,
      "created_at": "2026-06-30 18:12:05",
      "lastSeen": "2026-07-01T22:12:12.337Z"
    },
    {
      "adID": "2855388601465237",
      "source": "MP",
      "authorUrl": "https://www.facebook.com/marketplace/profile/100012624467516/?product_id=2855388601465237",
      "author": "Albano Lima Rizo",
      "postedTime": "2026-06-29T16:50:27.000Z",
      "title": "Zebra Blinds / Blackout",
      "description": "Contáctame aquí [hidden information]",
      "price": "$1",
      "lat": 27.9449854,
      "lon": -82.4583107,
      "location": "Tampa, FL",
      "imageUrl": "https://scontent-dfw5-2.xx.fbcdn.net/v/t39.84726-6/734767862_815446004867585_3630676578107001091_n.jpg?stp=dst-jpg_p720x720_tt6&_nc_cat=107&ccb=1-7&_nc_sid=92e707&_nc_ohc=6ZeBPSSGuV4Q7kNvwHTZSYY&_nc_oc=AdrGCQn05jxBMPdNtJRxs8LvlpJHb4OWCcuR8XvIsDGGDOUSkib8IlAvpQ4uOeJiUSs&_nc_zt=14&_nc_ht=scontent-dfw5-2.xx&_nc_gid=dlMistN69HJSMv3LmuXA4w&_nc_ss=7b2a8&oh=00_AQC6wNHDjZzyF1XF_jAu7rkMUfj-HTce_IrA6pI6y21B7A&oe=6A49C0DD",
      "adUrl": "https://www.facebook.com/marketplace/item/2855388601465237/",
      "priceChanged": 0,
      "priceChangedAt": null,
      "hidden": 0,
      "created_at": "2026-06-30 17:24:42",
      "lastSeen": "2026-07-01T15:12:10.443Z"
    },
    {
      "adID": "1667510114509875",
      "source": "MP",
      "authorUrl": "https://www.facebook.com/marketplace/profile/1337821800/?product_id=1667510114509875",
      "author": "Stacey Harris-hynes",
      "postedTime": "2026-06-30T05:12:33.000Z",
      "title": "Multi red, orange and yellow in this hanging pot",
      "description": "Beauty and color",
      "price": "$65",
      "lat": 29.8946952,
      "lon": -81.3145395,
      "location": "St Augustine, FL",
      "imageUrl": "https://scontent-dfw5-1.xx.fbcdn.net/v/t15.5256-10/736198399_1563664208719899_4588635129554621051_n.jpg?stp=dst-jpg_tt6&cstp=mx720x848&ctp=s720x848&_nc_cat=106&ccb=1-7&_nc_sid=d4195b&_nc_ohc=g8BANwRARXEQ7kNvwHWa_FP&_nc_oc=AdrhmDCX7HW2MXCFKdyDamOKnAWaVG-IWtOBo6gZsRI5zYH5BU4pkbFP1xIiAgKdkmg&_nc_zt=23&_nc_ht=scontent-dfw5-1.xx&_nc_gid=MwUqxamVh1ghPmoR-5m3nA&_nc_ss=7b2a8&oh=00_AQCAydcv-3c1b8otmCZPdkK54PMtIsu7uOXMubxKO3pz9A&oe=6A49E162",
      "adUrl": "https://www.facebook.com/marketplace/item/1667510114509875/",
      "priceChanged": 0,
      "priceChangedAt": null,
      "hidden": 0,
      "created_at": "2026-06-30 17:24:39",
      "lastSeen": "2026-07-01T15:14:59.001Z"
    },
    {
      "adID": "27445454091740755",
      "source": "MP",
      "authorUrl": "https://www.facebook.com/marketplace/profile/100090301632252/?product_id=27445454091740755",
      "author": "Emily Baptista",
      "postedTime": "2026-06-30T05:15:52.000Z",
      "title": "Out From Under Drew Seamless Ribbed Cropped Tank Top",
      "description": "Out From Under Drew seamless ribbed cropped tank. Pre-owned with no visible wear. Seamless construction, ribbed fabric, cropped length. Stretchy and form-fitting cut.",
      "price": "$25",
      "lat": 28.8021812,
      "lon": -81.731332,
      "location": "Tavares, FL",
      "imageUrl": "https://scontent-dfw6-1.xx.fbcdn.net/v/t39.84726-6/732477284_866600729836460_1141381551491229511_n.jpg?stp=dst-jpg_p960x960_tt6&_nc_cat=101&ccb=1-7&_nc_sid=92e707&_nc_ohc=1JW2JjzOQ6EQ7kNvwG6NyPn&_nc_oc=AdpTjYfquiwDhqDk2xkgR-CQFEMZN57DBHXMkE8NKaMYOh9uZ9brty7VEJu52BjBCZc&_nc_zt=14&_nc_ht=scontent-dfw6-1.xx&_nc_gid=ydMJcxEKBsdJIaLpJZ4cQA&_nc_ss=7b2a8&oh=00_AQDno1WDAVjwFoO3inMnR-6fSpgJrpqYLKolE0jE0pYEkA&oe=6A49BF1A",
      "adUrl": "https://www.facebook.com/marketplace/item/27445454091740755/",
      "priceChanged": 0,
      "priceChangedAt": null,
      "hidden": 0,
      "created_at": "2026-06-30 17:12:06",
      "lastSeen": "2026-07-01T15:14:53.726Z"
    },
    {
      "adID": "KLOV-381287",
      "source": "KLOV",
      "authorUrl": "https://forums.arcade-museum.com/members/kittybeater.35366/",
      "author": "kittybeater",
      "postedTime": "2026-06-30T14:54:26.000Z",
      "title": "Used Arcade Game Harnesses",
      "description": "Used Arcade Game Harnesses http://thearcadeboneyard.com/wire_harnesses_and_cables/wire_harnesses.php also have new jamma harnesses, edge connectors & 28 pin finger boards http://thearcadeboneyard.com/new_arcade_parts/new_jamma_harnesses_&_edge_connectors.php [email protected]",
      "price": "$0",
      "lat": 29.1871986,
      "lon": -82.1400923,
      "location": "Ocala, Florida",
      "imageUrl": "/images/klov-placeholder.png",
      "adUrl": "https://forums.arcade-museum.com/threads/381287/",
      "priceChanged": 0,
      "priceChangedAt": null,
      "hidden": 0,
      "created_at": "2026-06-30 16:25:28",
      "lastSeen": "2026-07-02T01:19:36.285Z"
    },
    {
      "adID": "2075596243023448",
      "source": "MP",
      "authorUrl": "https://www.facebook.com/marketplace/profile/100055848931840/?product_id=2075596243023448",
      "author": "Kelly's Furniture",
      "postedTime": "2026-06-30T16:09:44.000Z",
      "title": "Vintage pengo arcade game",
      "description": "This is a vintage arcade game. Two players. Sit across from each other. Original case. Works well look at it on Trout River Boulevard.",
      "price": "$375",
      "lat": 30.3262247,
      "lon": -81.6579179,
      "location": "Jacksonville, FL",
      "imageUrl": "https://scontent-dfw5-1.xx.fbcdn.net/v/t15.5256-10/519961364_1107646294571024_8029420294226648876_n.jpg?stp=dst-jpg_tt6&cstp=mx720x1280&ctp=s960x960&_nc_cat=105&ccb=1-7&_nc_sid=d4195b&_nc_ohc=bKd02Tkz_goQ7kNvwGV5sgk&_nc_oc=AdoNZ5nPmx42nSid4TANFsyCXTlnnoFQNIu0Wlu9BmC7JeyGkx2oG-l7Dx8vk57B5yg&_nc_zt=23&_nc_ht=scontent-dfw5-1.xx&_nc_gid=12ZUI8k8mIi6-AaMRLxn-g&_nc_ss=7b2a8&oh=00_AQDbpaiDxf2eQgFjky95ygMERJX6NMdhbj-BxkxQ-HMKRw&oe=6A49A8D6",
      "adUrl": "https://www.facebook.com/marketplace/item/2075596243023448/",
      "priceChanged": 0,
      "priceChangedAt": null,
      "hidden": 0,
      "created_at": "2026-06-30 16:21:36",
      "lastSeen": "2026-07-01T15:12:07.679Z"
    },
    {
      "adID": "3216493655219509",
      "source": "MP",
      "authorUrl": "https://www.facebook.com/marketplace/profile/100064089049153/?product_id=3216493655219509",
      "author": "Sean Nix",
      "postedTime": "2026-06-30T11:11:16.000Z",
      "title": "Pinball Manuals and Schematics",
      "description": "See Photos selling as a lot $75 Yes I still have them! Please do not ask! Will Not Ship Thanks for looking Have a great day!!",
      "price": "$35",
      "lat": 29.0491426,
      "lon": -82.4609331,
      "location": "Dunnellon, FL",
      "imageUrl": "https://scontent-dfw6-2.xx.fbcdn.net/v/t39.84726-6/733515089_987139914096258_7090395325153854580_n.jpg?stp=dst-jpg_p720x720_tt6&_nc_cat=109&ccb=1-7&_nc_sid=92e707&_nc_ohc=dxrFI6NIX3EQ7kNvwF_h0FR&_nc_oc=AdoWlqKz_k_zNSvft5WXhUbrfYovD5k0bJ8hiCtp7gZ1SPhpW4ewsAb0nPc2r14_E9g&_nc_zt=14&_nc_ht=scontent-dfw6-2.xx&_nc_gid=g5J7oDbXiwWzh8fub1maHQ&_nc_ss=7b2a8&oh=00_AQCxuJYGiieubXmS7miAPikwuAl_4mrAZJnszVlMEZxyuw&oe=6A498B47",
      "adUrl": "https://www.facebook.com/marketplace/item/3216493655219509/",
      "priceChanged": 0,
      "priceChangedAt": null,
      "hidden": 0,
      "created_at": "2026-06-30 13:14:59",
      "lastSeen": "2026-07-02T01:15:26.754Z"
    },
    {
      "adID": "998358612926193",
      "source": "MP",
      "authorUrl": "https://www.facebook.com/marketplace/profile/100008163312375/?product_id=998358612926193",
      "author": "Peter Jimolka",
      "postedTime": "2026-06-29T13:17:03.000Z",
      "title": "Original Vintage Arcade Game GLASS, MISS EUROPE (1960s) Plugs in. Changes(5)COLORS , every 30 Second",
      "description": "Boxed, Great Original Paint, plugs into wall 5 diffent flashing colors. Lights up! Carry room to room, changes color every 30 seconds Great for Game room, Office, Man Cave",
      "price": "$95",
      "lat": 30.4112904,
      "lon": -88.8279165,
      "location": "Ocean Springs, MS",
      "imageUrl": "https://scontent-dfw6-2.xx.fbcdn.net/v/t15.5256-10/428299067_876125947615337_2535643730309330170_n.jpg?stp=dst-jpg_tt6&cstp=mx720x1280&ctp=s960x960&_nc_cat=109&ccb=1-7&_nc_sid=3771cb&_nc_ohc=P_prz3zvnHYQ7kNvwGyF870&_nc_oc=AdrFcwTAckwOBx_O_gZQa_onJ--B5wIvodnSzt-fVLNjEymMhpV0XevVJNz1YtIk4k8&_nc_zt=23&_nc_ht=scontent-dfw6-2.xx&_nc_gid=RZVRfKF_04XpgLfiYMBH8A&_nc_ss=7b2a8&oh=00_AQBPMQRuNk6Rw6VL_Rfr6QZXScllOQQIaqrQVz2CYtylxA&oe=6A49A135",
      "adUrl": "https://www.facebook.com/marketplace/item/998358612926193/",
      "priceChanged": 0,
      "priceChangedAt": null,
      "hidden": 0,
      "created_at": "2026-06-30 13:12:32",
      "lastSeen": "2026-06-30T16:21:37.542Z"
    },
    {
      "adID": "2024748261753229",
      "source": "FB",
      "authorUrl": null,
      "author": "Benjamin Lamborn",
      "postedTime": "2026-06-30T00:10:05.955Z",
      "title": "Pinstadium Lights only. Not selling pinball machine. Stern, spooky, jersey jack",
      "description": "I have an extra pinstadium light. It helped with the darkness of my godzilla, I let it change colors but you can leave it on white. Lights only, not pinball machine for sale.",
      "price": "$150",
      "lat": 28.2441768,
      "lon": -82.7192671,
      "location": "NEW PORT RICHEY, FL",
      "imageUrl": "https://scontent-dfw6-2.xx.fbcdn.net/v/t39.30808-6/727415811_10162542041636556_6373422201961944905_n.jpg?stp=cp6_dst-jpegr_tt6&cstp=mx1392x3013&ctp=s590x590&_nc_cat=108&ccb=1-7&_nc_sid=aa7b47&_nc_ohc=lCbszpOOehgQ7kNvwHDy39v&_nc_oc=AdrdOUVxHDgOud93pnugUYchewC91A1alfJlhV4qYhavW7SH8SZYby0LZgH4-A6Mcpk&_nc_zt=23&se=-1&_nc_ht=scontent-dfw6-2.xx&_nc_gid=oTpmjWPUAZvjuyacYpFDzQ&_nc_ss=7b2a8&oh=00_AQBO2smP1nKEZdS3uYZWtMmE13Cke1lAV3p7nw7xlETtjA&oe=6A48F4BA",
      "adUrl": "https://www.facebook.com/commerce/listing/2024748261753229/",
      "priceChanged": 0,
      "priceChangedAt": null,
      "hidden": 0,
      "created_at": "2026-06-30 00:10:05",
      "lastSeen": "2026-06-30T01:09:58.184Z"
    },
    {
      "adID": "1875970883363665",
      "source": "MP",
      "authorUrl": "https://www.facebook.com/marketplace/profile/100002083374137/?product_id=1875970883363665",
      "author": "Mike Gray",
      "postedTime": "2026-06-29T21:23:17.000Z",
      "title": "Arcade game with 50 plus games",
      "description": "Working arcade game with multiple games included. Could use a little cleaning. $500 pick up in Pelham Alabama.",
      "price": "$500",
      "lat": 33.296224,
      "lon": -86.8436004,
      "location": "Helena, AL",
      "imageUrl": "https://scontent-dfw6-2.xx.fbcdn.net/v/t15.5256-10/730258675_1675842193622688_7191130979184471247_n.jpg?stp=dst-jpg_tt6&cstp=mx720x1280&ctp=s960x960&_nc_cat=108&ccb=1-7&_nc_sid=d4195b&_nc_ohc=Ppr8NDVUd5sQ7kNvwHbzahf&_nc_oc=Adr0pgQvvxko994_WFLtt5w-hdRBjwZ2Kye5-MBWU_d5jpTfKpcULy95oIGo2WoyNMA&_nc_zt=23&_nc_ht=scontent-dfw6-2.xx&_nc_gid=oJfb1FM_PaXyHOcRU8AdUQ&_nc_ss=7b2a8&oh=00_AQANQWFqnlaKvaxrPKUDM_JjIdsg1nKQenskiaGYkm5qqg&oe=6A48C86C",
      "adUrl": "https://www.facebook.com/marketplace/item/1875970883363665/",
      "priceChanged": 0,
      "priceChangedAt": null,
      "hidden": 0,
      "created_at": "2026-06-29 22:04:49",
      "lastSeen": "2026-06-30T16:21:36.353Z"
    },
    {
      "adID": "1512601667017738",
      "source": "MP",
      "authorUrl": "https://www.facebook.com/marketplace/profile/61554022450447/?product_id=1512601667017738",
      "author": "Cece Martinez",
      "postedTime": "2026-06-29T20:18:06.000Z",
      "title": "Arcade game screen",
      "description": "Final fight arcade screen and deck",
      "price": "$35",
      "lat": 27.9582131,
      "lon": -82.5318369,
      "location": "Obrien, FL",
      "imageUrl": "https://scontent-dfw5-2.xx.fbcdn.net/v/t39.84726-6/733524210_27288501940792590_6457638054101553509_n.jpg?stp=dst-jpg_s960x960_tt6&_nc_cat=100&ccb=1-7&_nc_sid=92e707&_nc_ohc=gNTNxb4s8zUQ7kNvwE5OS39&_nc_oc=AdqcULyUCwEkbYh0Xz1hzLZnZ2M7YzIovBf1bpsZ2w3tY4bpnPhA4gR7b3xkjwRENos&_nc_zt=14&_nc_ht=scontent-dfw5-2.xx&_nc_gid=_Pe6_tXoO0bgecuGsLqcOg&_nc_ss=7b2a8&oh=00_Af_PDfG5Sue9xPgSyrDO_Ry_MIuEfo3z40wId3qHrPktfg&oe=6A48C37D",
      "adUrl": "https://www.facebook.com/marketplace/item/1512601667017738/",
      "priceChanged": 0,
      "priceChangedAt": null,
      "hidden": 0,
      "created_at": "2026-06-29 21:04:50",
      "lastSeen": "2026-06-30T16:21:37.357Z"
    },
    {
      "adID": "KLOV-564268",
      "source": "KLOV",
      "authorUrl": "https://forums.arcade-museum.com/members/random_billybob.90752/",
      "author": "Random_Billybob",
      "postedTime": "2026-06-29T14:25:05.000Z",
      "title": "Empty Irem Lode Runner cab - $120",
      "description": "Empty Irem Lode Runner arcade cabinet with a Matsushita 19\" monitor and Jamma harness. Monitor is untested, but I can guarantee that it doesn't work. Some of the bottom corners are busted, but it is in otherwise decent shape with little to no water damage. This is a pretty rare cab, but not a game ...",
      "price": "$120",
      "lat": 33.5228885,
      "lon": -85.3446728,
      "location": "Ranburne, Alabama",
      "imageUrl": "https://sf.arcade-museum.com/data/attachments/860/860518-993f034d2e36c479d3b04753915850e0.jpg",
      "adUrl": "https://forums.arcade-museum.com/threads/564268/",
      "priceChanged": 0,
      "priceChangedAt": null,
      "hidden": 0,
      "created_at": "2026-06-29 15:09:10",
      "lastSeen": "2026-07-02T01:19:37.357Z"
    },
    {
      "adID": "KLOV-512184",
      "source": "KLOV",
      "authorUrl": "https://forums.arcade-museum.com/members/kittybeater.35366/",
      "author": "kittybeater",
      "postedTime": "2026-06-29T13:56:29.000Z",
      "title": "Bestco / VGA / 10 Inch Flat Panel Monitor $125",
      "description": "Bestco / VGA / 10 Inch Flat Panel Monitor (Serial No. BCSYNZ3GMJ) ( Was In A Lot Of Gold Machine) ( It Is Still In The Cabinet Panel For Protection In Shipment) (Item #2) $125.00 more pictures on this page of site Monitors The Arcade Boneyard, Arcade Parts Site Monitors For Arcade & Coin Operated M...",
      "price": "$125",
      "lat": 29.1871986,
      "lon": -82.1400923,
      "location": "Ocala, Florida",
      "imageUrl": "/images/klov-placeholder.png",
      "adUrl": "https://forums.arcade-museum.com/threads/512184/",
      "priceChanged": 0,
      "priceChangedAt": null,
      "hidden": 0,
      "created_at": "2026-06-29 14:08:01",
      "lastSeen": "2026-07-01T19:20:28.915Z"
    },
    {
      "adID": "KLOV-557313",
      "source": "KLOV",
      "authorUrl": "https://forums.arcade-museum.com/members/kittybeater.35366/",
      "author": "kittybeater",
      "postedTime": "2026-06-28T14:18:34.000Z",
      "title": "Coin Boxes",
      "description": "Bally midway, Williams, Taito, Gotlieb Pinball, Atari , Zaxxon, Sega, Over Under, others multiples on many of them available Coin Boxes, Holders & Covers The Arcade Boneyard, Arcade Parts Site Coin Boxes, Holders & Covers Page The Arcade Boneyard, New & Used Arcade & Coin Operated Machines, Parts ,...",
      "price": "$0",
      "lat": 29.1871986,
      "lon": -82.1400923,
      "location": "Ocala, Florida",
      "imageUrl": "/images/klov-placeholder.png",
      "adUrl": "https://forums.arcade-museum.com/threads/557313/",
      "priceChanged": 0,
      "priceChangedAt": null,
      "hidden": 0,
      "created_at": "2026-06-29 02:34:08",
      "lastSeen": "2026-07-01T01:15:57.959Z"
    },
    {
      "adID": "1397616155751804",
      "source": "MP",
      "authorUrl": "https://www.facebook.com/marketplace/profile/100009092386198/?product_id=1397616155751804",
      "author": "Paul B. Graves",
      "postedTime": "2026-06-28T17:38:56.000Z",
      "title": "Star Wars Atari Arcade Cabinet",
      "description": "(reposting again. deal fell through so lower price but firm) Star Wars Trilogy Arcade!! Includes Star Wars, The Empire Strikes Back, and Return of the Jedi!! Fantastic like-new condition, lot's of fun and great art work too! 100% working order. Adult owned, non-smoking home. $500 firm. Cash only. Front porch pick up in West Pensacola. Delivery can be discussed for a small fee. Thanks for looking, have a great day!",
      "price": "$500",
      "lat": 30.421309,
      "lon": -87.2169149,
      "location": "Pensacola, FL",
      "imageUrl": "https://scontent-dfw6-1.xx.fbcdn.net/v/t39.84726-6/731855238_4377711252441670_3732514856555855527_n.jpg?stp=dst-jpg_s960x960_tt6&_nc_cat=101&ccb=1-7&_nc_sid=92e707&_nc_ohc=2hWBLWuIDqoQ7kNvwHoyWM9&_nc_oc=AdoAN7INtElA5BUOcAhDudFl4EJie4sCCsjPbmjID3oyYY8psn7Qn-3R0UlFPuGT4ms&_nc_zt=14&_nc_ht=scontent-dfw6-1.xx&_nc_gid=Qn9tM_hMB3ji102mm0BQmg&_nc_ss=7b2a8&oh=00_Af913pBjhCq7xn1k4ePR2mbY_B-50RcQbK_nQgITH8kScQ&oe=6A478E63",
      "adUrl": "https://www.facebook.com/marketplace/item/1397616155751804/",
      "priceChanged": 0,
      "priceChangedAt": null,
      "hidden": 0,
      "created_at": "2026-06-29 02:00:52",
      "lastSeen": "2026-06-30T16:24:02.807Z"
    },
    {
      "adID": "902026556254979",
      "source": "MP",
      "authorUrl": "https://www.facebook.com/marketplace/profile/676820978/?product_id=902026556254979",
      "author": "Gaspar Ferreiro",
      "postedTime": "2026-06-28T19:56:04.000Z",
      "title": "Namco Maximum Tune/Mario Kart Arcade GP Arcade Cabinet",
      "description": "Authentic Namco Maximum Tune (can also suport Mario Kart) sit-down cabinet with a red racing seat. This arcade unit DOES NOTNINCLUDE THE Triforce hardware system (only connected it to show, monitor works). It includes a steering wheel, card dispenser, shifter, foot pedals, io boards amps, etc. (you will need to supply your game pc). The machine is constructed with a black and red plastic and metal housing.",
      "price": "$825",
      "lat": 34.0234337,
      "lon": -84.6154897,
      "location": "Kennesaw, GA",
      "imageUrl": "https://scontent-dfw6-2.xx.fbcdn.net/v/t39.84726-6/731916827_1600908031378060_3474254067138453068_n.jpg?stp=dst-jpg_p720x720_tt6&_nc_cat=110&ccb=1-7&_nc_sid=92e707&_nc_ohc=4KHP6Debn08Q7kNvwGkXHdD&_nc_oc=AdqHbwxPqHWzfUwk0VXiXEBexNNDbab0l3Nvn3wuEraTQGFKsiV2rs1OisW6bRufAdY&_nc_zt=14&_nc_ht=scontent-dfw6-2.xx&_nc_gid=o1zx1bK-lAyFCZDfdGCm4g&_nc_ss=7b2a8&oh=00_Af-zEWHbw_85nstej4OM_blzsPKDrAch6fwcubMUVEhVug&oe=6A47A5F0",
      "adUrl": "https://www.facebook.com/marketplace/item/902026556254979/",
      "priceChanged": 0,
      "priceChangedAt": null,
      "hidden": 0,
      "created_at": "2026-06-29 02:00:51",
      "lastSeen": "2026-06-30T16:21:36.799Z"
    },
    {
      "adID": "KLOV-563795",
      "source": "KLOV",
      "authorUrl": "https://forums.arcade-museum.com/members/digindug82.83438/",
      "author": "Digindug82",
      "postedTime": "2026-06-27T20:19:07.000Z",
      "title": "Various Style Coin Doors",
      "description": "Hi! Here we have a few different styles of coin doors I am selling, each country door has a number on it to make it easy looking at the pictures Door 1 is a Asahi Seiko single slot model NAD-2 that came off an Interstellar laser disc game. $100.00 now 85.00 shipped in the USA Door 2 is a coinco ove...",
      "price": "$100",
      "lat": 28.5551912,
      "lon": -81.7669488,
      "location": "Clermont, Florida",
      "imageUrl": "/images/klov-placeholder.png",
      "adUrl": "https://forums.arcade-museum.com/threads/563795/",
      "priceChanged": 0,
      "priceChangedAt": null,
      "hidden": 0,
      "created_at": "2026-06-27 21:12:47",
      "lastSeen": "2026-06-30T17:39:58.043Z"
    },
    {
      "adID": "1009930805235586",
      "source": "MP",
      "authorUrl": "https://www.facebook.com/marketplace/profile/100081427046424/?product_id=1009930805235586",
      "author": "Daniel Poole",
      "postedTime": "2026-06-27T20:08:14.000Z",
      "title": "Asteroids metal sign video Game retro style",
      "description": "Retro Asteroids sign Item is sealed in plastic wrap, looks like a fun game for fans of classic arcade games.",
      "price": "$28",
      "lat": 34.1206564,
      "lon": -84.0043513,
      "location": "Buford, GA",
      "imageUrl": "https://scontent-dfw6-1.xx.fbcdn.net/v/t39.84726-6/732733460_1332828585639591_7832456644223864580_n.jpg?stp=dst-jpg_p720x720_tt6&_nc_cat=101&ccb=1-7&_nc_sid=92e707&_nc_ohc=btAkx4zdYCIQ7kNvwG0JMyY&_nc_oc=Adqsvobx5PJGF31drdgxikl9XrKcvjNBBQHjd-cQXXwdHqF31hfoMS15HjRggrOy2Po&_nc_zt=14&_nc_ht=scontent-dfw6-1.xx&_nc_gid=1chmG_vnsbG8K5CWGK3AvA&_nc_ss=7b2a8&oh=00_AQB1gRkxKxgeRSyMBxBIpeBFWNcLXHvEYD8KQsXtBhmWKA&oe=6A4A7D27",
      "adUrl": "https://www.facebook.com/marketplace/item/1009930805235586/",
      "priceChanged": 0,
      "priceChangedAt": null,
      "hidden": 0,
      "created_at": "2026-06-27 21:04:55",
      "lastSeen": "2026-07-01T06:06:49.801Z"
    },
    {
      "adID": "1191577733108646",
      "source": "MP",
      "authorUrl": "https://www.facebook.com/marketplace/profile/100042840062437/?product_id=1191577733108646",
      "author": "Trevor Ellison",
      "postedTime": "2026-06-27T16:19:52.000Z",
      "title": "Star Wars Arcade for Sega 32X",
      "description": "Star Wars Arcade for Sega 32X. Great condition. $15 or best offer.",
      "price": "$15",
      "lat": 33.3975472,
      "lon": -84.5898256,
      "location": "Peachtree City, GA",
      "imageUrl": "https://scontent-dfw6-2.xx.fbcdn.net/v/t39.84726-6/733187267_1583724603360609_4231812660606657584_n.jpg?stp=dst-jpg_p720x720_tt6&_nc_cat=109&ccb=1-7&_nc_sid=92e707&_nc_ohc=A3Ko3zV1TMEQ7kNvwH1Ez-b&_nc_oc=AdqJ1LQwhczAMksHpOhG-FMS0-vnRFEgOhN7COF10cIjzqQ72UEyMS1uL9aOUhRJZkE&_nc_zt=14&_nc_ht=scontent-dfw6-2.xx&_nc_gid=wz2h8LrzLY4yJEs-reXfSw&_nc_ss=7b2a8&oh=00_AQAH1Hs0V_RgZf-XbRVZxzsLP7NAXG7fPQ_6DDIDoA7T7Q&oe=6A4A66BA",
      "adUrl": "https://www.facebook.com/marketplace/item/1191577733108646/",
      "priceChanged": 0,
      "priceChangedAt": null,
      "hidden": 0,
      "created_at": "2026-06-27 17:05:14",
      "lastSeen": "2026-07-01T06:06:50.310Z"
    },
    {
      "adID": "KLOV-498705",
      "source": "KLOV",
      "authorUrl": "https://forums.arcade-museum.com/members/kittybeater.35366/",
      "author": "kittybeater",
      "postedTime": "2026-07-01T20:27:54.000Z",
      "title": "Tekken 2 Jamma PCB (Working) $124.99",
      "description": "Tekken 2 Jamma PCB (Working) (Item #20) $124.99 PCB's R - Z The Arcade Boneyard, Arcade Parts Site PCB's (Circuit Boards) PCB's R - Z For Arcade & Coin Operated Machines The Arcade Boneyard, New & Used Arcade & Coin Operated Machines, Parts , Manuals thearcadeboneyard.com",
      "price": "$124",
      "lat": 29.1871986,
      "lon": -82.1400923,
      "location": "Ocala, Florida",
      "imageUrl": "/images/klov-placeholder.png",
      "adUrl": "https://forums.arcade-museum.com/threads/498705/",
      "priceChanged": 0,
      "priceChangedAt": null,
      "hidden": 0,
      "created_at": "2026-06-27 15:15:30",
      "lastSeen": "2026-07-02T01:19:35.538Z"
    },
    {
      "adID": "4455572051388037",
      "source": "FB",
      "authorUrl": null,
      "author": "Marc Richter",
      "postedTime": "2026-06-28T01:02:33.093Z",
      "title": "Tekken 3 arcade machine in excellent condition, 100% working.",
      "description": "Tekken 3 in great condition 100% working. Set to free play. Comes with beautiful LCD monitor for years of problem free fun play. Can deliver locally.",
      "price": "$875",
      "lat": 28.1866014,
      "lon": -82.366121,
      "location": "WESLEY CHAPEL, FL",
      "imageUrl": "https://scontent-dfw5-1.xx.fbcdn.net/v/t39.30808-6/731444146_10242948334588270_319462232030511107_n.jpg?stp=dst-jpg_tt6&cstp=mx1536x2048&ctp=s590x590&_nc_cat=111&ccb=1-7&_nc_sid=aa7b47&_nc_ohc=zRx83UGp5D4Q7kNvwG2OHX7&_nc_oc=AdomGvNTKn0ekFfV-vAUUrO5i5Q56jC12ysheEUW6iDUqlKJy53pCug0UvNJ1g_k1jw&_nc_zt=23&_nc_ht=scontent-dfw5-1.xx&_nc_gid=mhtyLGHUvoUtvJ7g1UGfsA&_nc_ss=7b2a8&oh=00_AQAdlHSfH5_v9e06yh4XcT0E6j7IYw0l5_5KcsAvxgQC0g&oe=6A4B8554",
      "adUrl": "https://www.facebook.com/commerce/listing/4455572051388037/",
      "priceChanged": 0,
      "priceChangedAt": null,
      "hidden": 0,
      "created_at": "2026-06-27 13:00:55",
      "lastSeen": "2026-07-02T01:02:33.974Z"
    },
    {
      "adID": "1714705549553494",
      "source": "MP",
      "authorUrl": "https://www.facebook.com/marketplace/profile/61578552173428/?product_id=1714705549553494",
      "author": "Jay Reeves",
      "postedTime": "2026-06-26T22:34:47.000Z",
      "title": "Galaga Arcade Marquee Panel",
      "description": "Black acrylic panel with a Galaga pixel art design. This rectangular piece has a smooth finish and vibrant multi-colored graphics. It is a decorative item for a game room or arcade cabinet.",
      "price": "$20",
      "lat": 33.3870578,
      "lon": -84.2829784,
      "location": "Hampton, GA",
      "imageUrl": "https://scontent-dfw6-2.xx.fbcdn.net/v/t15.5256-10/732504565_1375132931196804_614184865746505871_n.jpg?stp=dst-jpg_tt6&cstp=mx720x1280&ctp=s960x960&_nc_cat=108&ccb=1-7&_nc_sid=d4195b&_nc_ohc=ebrVodYL9hcQ7kNvwFKH7Gs&_nc_oc=AdpHfy6dUBpr6VWSC876BxFkKDQzNV0avBKW78NK969Ev2nSk4HI3V99Z57rt0J4PFU&_nc_zt=23&_nc_ht=scontent-dfw6-2.xx&_nc_gid=e9KzOwIoBeDV69H0ud14pA&_nc_ss=7b2a8&oh=00_AQC-lk2q5I7wPU0eAUly_gvxf_zPEyxzC7ptcrIFPMcTlA&oe=6A4A6F29",
      "adUrl": "https://www.facebook.com/marketplace/item/1714705549553494/",
      "priceChanged": 0,
      "priceChangedAt": null,
      "hidden": 0,
      "created_at": "2026-06-27 12:33:26",
      "lastSeen": "2026-07-01T06:10:30.217Z"
    },
    {
      "adID": "1024766013340116",
      "source": "FB",
      "authorUrl": null,
      "author": "Anthony Ward",
      "postedTime": "2026-06-28T01:08:52.687Z",
      "title": "Big Event Golf",
      "description": "I have a Big Event Golf arcade machine. Own a piece of nostalgic history. Before Golden Tee. Do not expect it to be in perfect condition as it is from 1986, but everyth... See more",
      "price": "$320",
      "lat": 27.9449854,
      "lon": -82.4583107,
      "location": "TAMPA, FL",
      "imageUrl": "https://scontent-dfw5-1.xx.fbcdn.net/v/t39.30808-6/731253032_3541431712671266_1665902000841851541_n.jpg?stp=cp6_dst-jpg_tt6&cstp=mx1536x2048&ctp=s590x590&_nc_cat=105&ccb=1-7&_nc_sid=aa7b47&_nc_ohc=6-ILhvJT8HUQ7kNvwGTh5RH&_nc_oc=AdreK8-dQV_7pxMvrVuWVw8Q_3a4ixi0Quf5dAJhUVsGwbztkuX4JhtirHcRPlN-iBg&_nc_zt=23&_nc_ht=scontent-dfw5-1.xx&_nc_gid=ZuHIVvnuLK9P8YW3jq2mFQ&_nc_ss=7b2a8&oh=00_AQCUGgWZAb24WF5f2ipFAOCuw_hVCDwByu0etpD0fB_x3g&oe=6A4B9C22",
      "adUrl": "https://www.facebook.com/commerce/listing/1024766013340116/",
      "priceChanged": 0,
      "priceChangedAt": null,
      "hidden": 0,
      "created_at": "2026-06-27 12:31:56",
      "lastSeen": "2026-07-02T01:08:53.105Z"
    },
    {
      "adID": "KLOV-545491",
      "source": "KLOV",
      "authorUrl": "https://forums.arcade-museum.com/members/jjhudgins.80749/",
      "author": "jjhudgins",
      "postedTime": "2026-06-26T21:32:42.000Z",
      "title": "Let's make a DEAL! BUY 2 or more Shipping is FREE Buy 3 or more get a $10 Manual FREE *Parts & Operating Manuals Schematics Diagrams * See Below",
      "description": "All manuals are $5 to ship BUY 2 or more Shipping is FREE Buy 3 or more get a $10 Manual FREE + FREE Shipping Altered Beast$25.00avengers$10.00Captain America$10.00Centipede$20.00Chexx$10.00Cinemat system$10.00Congo Bongo$15.00Cruis'n USA$20.00Deluxe to Elevator Action$10.00Donkey Kong 2 board$15.0...",
      "price": "$10",
      "lat": 33.2588817,
      "lon": -86.8295337,
      "location": "Alabama",
      "imageUrl": "https://sf.arcade-museum.com/data/attachments/776/776831-1ce0192247d637631590530126bbc0dd.jpg",
      "adUrl": "https://forums.arcade-museum.com/threads/545491/",
      "priceChanged": 0,
      "priceChangedAt": null,
      "hidden": 0,
      "created_at": "2026-06-26 19:10:55",
      "lastSeen": "2026-06-30T12:18:21.712Z"
    },
    {
      "adID": "27282259201394945",
      "source": "MP",
      "authorUrl": "https://www.facebook.com/marketplace/profile/1781109444/?product_id=27282259201394945",
      "author": "Bart Mecum",
      "postedTime": "2026-06-26T18:39:24.000Z",
      "title": "New FS-U Universal Fluorescent Starter replaces FS2, 4, 5 Arcade Pinball Machine",
      "description": "New FS-U Universal Fluorescent Starter replaces FS2, 4, 5 Arcade Pinball Machine",
      "price": "$10",
      "lat": 27.928464,
      "lon": -82.2880508,
      "location": "Brandon, FL",
      "imageUrl": "https://scontent-dfw5-2.xx.fbcdn.net/v/t39.84726-6/731588920_1327741595651677_1192579354863791964_n.jpg?stp=dst-jpg_s960x960_tt6&_nc_cat=104&ccb=1-7&_nc_sid=92e707&_nc_ohc=mtjAjfm-99sQ7kNvwHLhIbn&_nc_oc=AdqVoCNtAYm5q9R62RDxqbR1QEdW8LsWQYm8WBTxuQ7GZPSjRbkSU05mVbJqNI8cChw&_nc_zt=14&_nc_ht=scontent-dfw5-2.xx&_nc_gid=QTCYPhLhRo8lO3N4kluzhw&_nc_ss=7b2a8&oh=00_Af9tITksleSuw-asiTTZRHg0eb1S_MhlaEN__PkDFCy36Q&oe=6A44B832",
      "adUrl": "https://www.facebook.com/marketplace/item/27282259201394945/",
      "priceChanged": 0,
      "priceChangedAt": null,
      "hidden": 0,
      "created_at": "2026-06-26 19:04:59",
      "lastSeen": "2026-07-01T16:34:51.299Z"
    },
    {
      "adID": "1727114011637456",
      "source": "MP",
      "authorUrl": "https://www.facebook.com/marketplace/profile/1666031625/?product_id=1727114011637456",
      "author": "Lee Smith",
      "postedTime": "2026-06-21T20:15:28.000Z",
      "title": "Pinball Machine",
      "description": "Make me an offer , needs minor repairs",
      "price": "$350",
      "lat": 30.8327022,
      "lon": -83.2784851,
      "location": "Valdosta, GA",
      "imageUrl": "https://scontent-dfw5-2.xx.fbcdn.net/v/t39.84726-6/728861569_1278089951064301_7952330594510795467_n.jpg?stp=dst-jpg_p720x720_tt6&_nc_cat=107&ccb=1-7&_nc_sid=92e707&_nc_ohc=YBfewYoH_q0Q7kNvwFzELFY&_nc_oc=AdoT44zN0fvSHqYRh0tF_tOqdxuzNydZGlhO-J0Q5nGEmOf8l8YHwKPD1c0E6w5GQJI&_nc_zt=14&_nc_ht=scontent-dfw5-2.xx&_nc_gid=bPuPhvY1MavvrSpXw-L-pQ&_nc_ss=7b2a8&oh=00_Af_9kgVV48UTRRigRQ_DplfUbOhmyFbNHyaxdCeOKZuyEg&oe=6A4879D0",
      "adUrl": "https://www.facebook.com/marketplace/item/1727114011637456/",
      "priceChanged": 0,
      "priceChangedAt": null,
      "hidden": 0,
      "created_at": "2026-06-26 15:06:38",
      "lastSeen": "2026-06-29T15:39:16.125Z"
    },
    {
      "adID": "1656345528806363",
      "source": "MP",
      "authorUrl": "https://www.facebook.com/marketplace/profile/1472980766/?product_id=1656345528806363",
      "author": "John Russo",
      "postedTime": "2026-06-26T10:57:25.000Z",
      "title": "Tekken 3 coin operated arcade game",
      "description": "Great looking conversion into what was a Mortal Kombat cabinet. 25 inch CRT is bright and clear Works 100%. Good for your man cave, your Airbnb, or your commercial application. Can arrange local delivery nationwide shipping always glad to take trades for other coin games.",
      "price": "$900",
      "lat": 27.7712264,
      "lon": -82.6340259,
      "location": "St Petersburg, FL",
      "imageUrl": "https://scontent-dfw6-1.xx.fbcdn.net/v/t15.5256-10/576428742_25048435228158115_2491860292997653112_n.jpg?stp=dst-jpg_tt6&cstp=mx720x1280&ctp=s960x960&_nc_cat=101&ccb=1-7&_nc_sid=d4195b&_nc_ohc=07qhzhOCdXYQ7kNvwEyN5Mi&_nc_oc=Adq8L5v91RQgudVoaqWRojrHb6ZtnP2gWYTPoEeDXcnJVfHkVfaiB83t-8di6fbAa2A&_nc_zt=23&_nc_ht=scontent-dfw6-1.xx&_nc_gid=QlanAEx-GtV7CSuVKzGHZw&_nc_ss=7b2a8&oh=00_AQAezmTek5g5ySHXxd_hjZDsPlaWrFrW7V2MwD_i5_hb1Q&oe=6A49B524",
      "adUrl": "https://www.facebook.com/marketplace/item/1656345528806363/",
      "priceChanged": 0,
      "priceChangedAt": null,
      "hidden": 0,
      "created_at": "2026-06-26 11:04:58",
      "lastSeen": "2026-06-30T15:48:57.351Z"
    },
    {
      "adID": "1004231748969696",
      "source": "MP",
      "authorUrl": "https://www.facebook.com/marketplace/profile/100015523176457/?product_id=1004231748969696",
      "author": "Ella Haney",
      "postedTime": "2026-06-25T18:48:30.000Z",
      "title": "Arcade Machine",
      "description": "Works & turns on- comes with how to work info- has been sitting in a indoor storage space so could use a good cleaning. Cash only- must pick up",
      "price": "$160",
      "lat": 33.6190031,
      "lon": -83.8674052,
      "location": "Oxford, GA",
      "imageUrl": "https://scontent-dfw5-2.xx.fbcdn.net/v/t39.84726-6/731339077_2228808367962818_78971362888682843_n.jpg?stp=dst-jpg_s960x960_tt6&_nc_cat=104&ccb=1-7&_nc_sid=92e707&_nc_ohc=Nj84aqXxCFoQ7kNvwEdXTZY&_nc_oc=AdosoVbS9-pVGdMqFRAYT3mMBfVQNzU0y7Lu2LOs_Qz6hyF0_mKmx6bv_e0kdcsfF3o&_nc_zt=14&_nc_ht=scontent-dfw5-2.xx&_nc_gid=NgPCTXWwMT1zw0781ZuBWQ&_nc_ss=7b2a8&oh=00_AQB0k1RneEAbGbDDL9_kqIJJEp7ph88qRt8WTbD6VnRbjA&oe=6A489BA9",
      "adUrl": "https://www.facebook.com/marketplace/item/1004231748969696/",
      "priceChanged": 0,
      "priceChangedAt": null,
      "hidden": 0,
      "created_at": "2026-06-25 19:04:57",
      "lastSeen": "2026-06-29T21:33:27.649Z"
    },
    {
      "adID": "1370466454935133",
      "source": "MP",
      "authorUrl": "https://www.facebook.com/marketplace/profile/1065080449/?product_id=1370466454935133",
      "author": "Robert Kiedinger",
      "postedTime": "2026-06-25T16:46:19.000Z",
      "title": "Pinball Scoring LEDS and Interconnect Board",
      "description": "There is 1 seven-digit display, 1 display for credits and random number, and the interconnect board for the displays. They are original from a Williams system 7 machine, functioning 100%, no frizzing or missing numbers. $20 each. or $50 for all 3. Will ship for cost.",
      "price": "$1",
      "lat": 33.3392842,
      "lon": -84.6485417,
      "location": "Sharpsburg, GA",
      "imageUrl": "https://scontent-dfw6-2.xx.fbcdn.net/v/t39.84726-6/731736038_2014383632499565_8301082935377919126_n.jpg?stp=dst-jpg_p720x720_tt6&_nc_cat=108&ccb=1-7&_nc_sid=92e707&_nc_ohc=R7KrXI5ph3wQ7kNvwGlkYdT&_nc_oc=AdrDB1Xc_DkY216gRYCSyh5oTdKH15I32wz4T3We5M3BSrqf--VmpxW0rMU81Y5TJG0&_nc_zt=14&_nc_ht=scontent-dfw6-2.xx&_nc_gid=XVX_a3dG7zvJ03_dx5xRsQ&_nc_ss=7b2a8&oh=00_AQAnoCge77GJq450noJUhornk_Une5rI9He9B6Yvub5SRg&oe=6A48D2C8",
      "adUrl": "https://www.facebook.com/marketplace/item/1370466454935133/",
      "priceChanged": 0,
      "priceChangedAt": null,
      "hidden": 0,
      "created_at": "2026-06-25 17:06:06",
      "lastSeen": "2026-06-29T21:33:27.682Z"
    },
    {
      "adID": "1595430692013898",
      "source": "MP",
      "authorUrl": "https://www.facebook.com/marketplace/profile/1065080449/?product_id=1595430692013898",
      "author": "Robert Kiedinger",
      "postedTime": "2026-06-25T16:46:09.000Z",
      "title": "New Lady Luck Pinball Machine Backglass",
      "description": "New backglass for a Lucky Lady pinball machine. Dimensions- 24.75\"H x 26.\"W. Would be a replacement for a backglass except that the glasscutter mismeasured and it's 1/8\" too tall. So it's a great work of art and conversation piece as is.",
      "price": "$60",
      "lat": 33.3392842,
      "lon": -84.6485417,
      "location": "Sharpsburg, GA",
      "imageUrl": "https://scontent-dfw6-1.xx.fbcdn.net/v/t39.84726-6/731357503_1053490800684939_6626246038794732238_n.jpg?stp=dst-jpg_p720x720_tt6&_nc_cat=101&ccb=1-7&_nc_sid=92e707&_nc_ohc=jjIO0RMrzuoQ7kNvwEoaseD&_nc_oc=AdrGLSBbfDzGCPBc3PK1BoAGAHV_Pks4grEIHkHBtTofECTMLOzm73lK0tEtaxhGwDU&_nc_zt=14&_nc_ht=scontent-dfw6-1.xx&_nc_gid=FdZ6MIkkH5jplk7edRZcXg&_nc_ss=7b2a8&oh=00_AQADWJF9C3ldUwjORA77EbTBjdi_G3GcX4Fa73L25r1n2A&oe=6A48A0D8",
      "adUrl": "https://www.facebook.com/marketplace/item/1595430692013898/",
      "priceChanged": 0,
      "priceChangedAt": null,
      "hidden": 0,
      "created_at": "2026-06-25 17:06:06",
      "lastSeen": "2026-06-29T21:33:27.717Z"
    },
    {
      "adID": "PI-216824",
      "source": "PS",
      "authorUrl": "https://pinside.com/pinball/community/pinsiders/blessed/market",
      "author": "Blessed",
      "postedTime": "2026-06-25T23:14:27.896Z",
      "title": "Freedom EM 2nd Version",
      "description": "Used - shows wear but 100% working and clean - “Plays well. Everything in Backbox, including score reels cleaned within the last year and a half. All switches under playfield and inside cabinet cleaned as well. Flippers, pop bu...”",
      "price": "$500",
      "lat": 33.8389977,
      "lon": -83.9007382,
      "location": "Loganville, GA",
      "imageUrl": "https://imgproxy.pinside.com/fsM0JDAHQC4KNNW_nMMDcNLXWyHfSNdRst24bxUnUhg/rs:fit:640:480/fn:pinside_7d5891d42747/enc/pJ859sToWD98GZpuD45hTE9NvVe2eZIbLrmYc54l5C4BeDOiSMDXG8kZzMIVIEWMD2jCdhg_7S_LySl3qxCNkf07MK8q0iZus7VxKL0ZbkV32ptZ0tZR-qUteNxZU9mb.jpg",
      "adUrl": "https://pinside.com/pinball/market/classifieds/ad/216824",
      "priceChanged": 0,
      "priceChangedAt": null,
      "hidden": 0,
      "created_at": "2026-06-25 14:11:16",
      "lastSeen": "2026-07-01T06:12:19.110Z"
    },
    {
      "adID": "KLOV-556509",
      "source": "KLOV",
      "authorUrl": "https://forums.arcade-museum.com/members/jjhudgins.80749/",
      "author": "jjhudgins",
      "postedTime": "2026-06-30T16:46:50.000Z",
      "title": "19\" & 25\" Degauss Coils with ground straps for 25\" $25 shipped UPS",
      "description": "19\" & 25\" Degauss Coils with ground straps for 25\" $25 shipped UPS",
      "price": "$25",
      "lat": 33.2588817,
      "lon": -86.8295337,
      "location": "Alabama",
      "imageUrl": "/images/klov-placeholder.png",
      "adUrl": "https://forums.arcade-museum.com/threads/556509/",
      "priceChanged": 0,
      "priceChangedAt": null,
      "hidden": 0,
      "created_at": "2026-06-25 11:58:20",
      "lastSeen": "2026-06-30T19:18:56.006Z"
    },
    {
      "adID": "KLOV-554639",
      "source": "KLOV",
      "authorUrl": "https://forums.arcade-museum.com/members/kittybeater.35366/",
      "author": "kittybeater",
      "postedTime": "2026-06-24T15:02:04.000Z",
      "title": "Coin Boxes, Coin Box Holders, Coin Box Covers for sale",
      "description": "Coin Boxes, Coin Box Holders, Coin Box Covers for sale Coin Boxes, Holders & Covers The Arcade Boneyard, Arcade Parts Site Coin Boxes, Holders & Covers Page The Arcade Boneyard, New & Used Arcade & Coin Operated Machines, Parts , Manuals thearcadeboneyard.com",
      "price": "$0",
      "lat": 29.1871986,
      "lon": -82.1400923,
      "location": "Ocala, Florida",
      "imageUrl": "/images/klov-placeholder.png",
      "adUrl": "https://forums.arcade-museum.com/threads/554639/",
      "priceChanged": 0,
      "priceChangedAt": null,
      "hidden": 0,
      "created_at": "2026-06-25 11:58:19",
      "lastSeen": "2026-06-30T14:53:13.727Z"
    },
    {
      "adID": "KLOV-552819",
      "source": "KLOV",
      "authorUrl": "https://forums.arcade-museum.com/members/jjhudgins.80749/",
      "author": "jjhudgins",
      "postedTime": "2026-06-24T03:28:52.000Z",
      "title": "G07 K4600 k4900 u2000 k7400 k7000 YOKES",
      "description": "Cr31 k7000 SOLD GO7 k4600 SOLD K4900 intermediate, and late versions Cr23 k7000, k7203 k7201 (sold) U2000 K7400 25\" k7000 see pics for ohms $65 plus shipping",
      "price": "$65",
      "lat": 33.2588817,
      "lon": -86.8295337,
      "location": "Alabama",
      "imageUrl": "https://sf.arcade-museum.com/data/attachments/797/797332-f7c6671a8d9c5dd7a6f6a4ec7756518b.jpg",
      "adUrl": "https://forums.arcade-museum.com/threads/552819/",
      "priceChanged": 0,
      "priceChangedAt": null,
      "hidden": 0,
      "created_at": "2026-06-25 11:58:19",
      "lastSeen": "2026-06-30T12:18:46.788Z"
    },
    {
      "adID": "KLOV-564536",
      "source": "KLOV",
      "authorUrl": "https://forums.arcade-museum.com/members/shawn1976.38848/",
      "author": "Shawn1976",
      "postedTime": "2026-07-01T15:44:36.000Z",
      "title": "Red and Black Lollipop Joystick Shafts",
      "description": "A set that I've had for quite sometime. Asking $25 shipped for the set or best offer. Shoot me a pm if interested.",
      "price": "$25",
      "lat": 29.8946952,
      "lon": -81.3145395,
      "location": "Saint Augustine, Florida",
      "imageUrl": "https://sf.arcade-museum.com/data/attachments/862/862461-0d9c604463834809d8eab2d2b8e058a7.jpg",
      "adUrl": "https://forums.arcade-museum.com/threads/564536/",
      "priceChanged": 0,
      "priceChangedAt": null,
      "hidden": 0,
      "created_at": "2026-06-25 11:58:18",
      "lastSeen": "2026-07-02T01:19:35.815Z"
    },
    {
      "adID": "1533848331559933",
      "source": "MP",
      "authorUrl": "https://www.facebook.com/marketplace/profile/100066657743451/?product_id=1533848331559933",
      "author": "Michael Bucholtz",
      "postedTime": "2026-06-24T13:52:52.000Z",
      "title": "Golden Tee Tournament Edition Arcade Machine – Original Cabinet tested fully working",
      "description": "Fully tested and working. Golden Tee Tournament Edition arcade machine by Incredible Technologies. Original full-size arcade cabinet with trackball controls, coin door, CRT monitor, and game board still installed. Cabinet appears largely complete but has been in storage and is being sold as-is, untested. Features: Original Golden Tee Tournament Edition artwork Full-size stand-up arcade cabinet Trackball control panel Coin door and coin mechanisms present CRT monitor installed Original game board appears present inside cabinet Great restoration project or man-cave/game room piece Condition: Fully functional Cabinet has cosmetic wear, chips, and scratches",
      "price": "$450",
      "lat": 28.5756641,
      "lon": -81.7482915,
      "location": "Minneola, FL",
      "imageUrl": "https://scontent-dfw5-1.xx.fbcdn.net/v/t15.5256-10/729185999_1535720207950170_1309002535502064370_n.jpg?stp=dst-jpg_tt6&cstp=mx720x1280&ctp=s960x960&_nc_cat=106&ccb=1-7&_nc_sid=d4195b&_nc_ohc=xeaPYKGLvkcQ7kNvwEkzdVS&_nc_oc=AdoXI7oWzcxuUpU_mMMrfxDyKYdYp-IrNOq3lXvFzR-xEhun3KJ4GpJzkAwQYE9zMnI&_nc_zt=23&_nc_ht=scontent-dfw5-1.xx&_nc_gid=jzmltHZltrOWvQ66taOa9g&_nc_ss=7b2a8&oh=00_Af-Yfqa4xwGpXiOC6c1gpz6s4Ogyj9USb2cAP6C6IRA4ug&oe=6A47E5E9",
      "adUrl": "https://www.facebook.com/marketplace/item/1533848331559933/",
      "priceChanged": 0,
      "priceChangedAt": null,
      "hidden": 0,
      "created_at": "2026-06-25 11:21:22",
      "lastSeen": "2026-06-29T06:06:36.051Z"
    },
    {
      "adID": "1681924132857881",
      "source": "MP",
      "authorUrl": "https://www.facebook.com/marketplace/profile/61565190981866/?product_id=1681924132857881",
      "author": "Julian Nygren",
      "postedTime": "2026-06-24T01:19:03.000Z",
      "title": "Pending - SNK Street Smart dedicated arcade machine - working",
      "description": "Original dedicated SNK Street Smart arcade machine. Game is working and in overall good condition, but could still use a little bit of TLC. Excellent lite project. Little to no water damage, has some damage on the edges, but it overall pretty decent. I've done some work to it, but selling for what I have into it to make room for other projects. Comes with back door, and I can install new locks if needed. $325, located in Ranburne AL.",
      "price": "$325",
      "lat": 33.5228885,
      "lon": -85.3446728,
      "location": "Ranburne, AL",
      "imageUrl": "https://scontent-dfw6-2.xx.fbcdn.net/v/t15.5256-10/730621158_1712064777205694_5067932360059512286_n.jpg?stp=dst-jpg_tt6&cstp=mx720x1280&ctp=s960x960&_nc_cat=108&ccb=1-7&_nc_sid=d4195b&_nc_ohc=S6Oezye-n0QQ7kNvwGdCfDb&_nc_oc=Adr6p-G1KyWEcsoD1hPVszxrCG8Zl4suqE1ZBHpNagxaiutQ0xBBag-0ynPowW3_b78&_nc_zt=23&_nc_ht=scontent-dfw6-2.xx&_nc_gid=9h4mL3Qq0C5FrhgrD7acZA&_nc_ss=7b2a8&oh=00_Af_HEqLhuwWItSScUhYQGz2d6iu7ey_ukRvjvPjgfCjpsg&oe=6A47D0BA",
      "adUrl": "https://www.facebook.com/marketplace/item/1681924132857881/",
      "priceChanged": 0,
      "priceChangedAt": null,
      "hidden": 0,
      "created_at": "2026-06-25 11:21:21",
      "lastSeen": "2026-06-29T06:06:36.354Z"
    },
    {
      "adID": "1639860653870129",
      "source": "FB",
      "authorUrl": null,
      "author": "Richard Thompson",
      "postedTime": "2026-06-25T00:08:39.087Z",
      "title": "PAC MAN MONITOR GLASS BEZEL ONLY $50 OBO!",
      "description": "This PAC MAN MONITOR GLASS BEZEL is a collectible replacement part for an arcade gaming machine, specifically designed for the game Pac-Man. Produced by Bally Midway, this bezel adds a sleek and authentic touch to the monitor of a vintage arcade game, enhancing the overall gaming experience for enthusiasts. Perfect for restoring or customizing a classic arcade machine, this PAC MAN MONITOR GLASS BEZEL is a must-have for collectors and gamers looking to preserve the nostalgia ... See more",
      "price": "$50",
      "lat": 32.2998686,
      "lon": -90.1830408,
      "location": "JACKSON, MS",
      "imageUrl": "https://scontent-dfw6-1.xx.fbcdn.net/v/t39.30808-6/689495336_2457459551439313_1413917428850761011_n.jpg?stp=dst-jpg_tt6&cstp=mx640x480&ctp=s590x590&_nc_cat=103&ccb=1-7&_nc_sid=aa7b47&_nc_ohc=p3xhzX2_FqcQ7kNvwEWiGoM&_nc_oc=Adr-ovNE2viiSeIlb8A45nvp1u03qptoBAzpqDZouumFHvRe0dBToGjWWNMdXF4UoA4&_nc_zt=23&_nc_ht=scontent-dfw6-1.xx&_nc_gid=hS80aVt6mK0Zr8RcsrJGVA&_nc_ss=7b2a8&oh=00_AQAkdr_7cbKrQoyPgo5c7ENgRKitw8Nhd6XE6E_ASW6lmA&oe=6A4B9B06",
      "adUrl": "https://www.facebook.com/commerce/listing/1639860653870129/",
      "priceChanged": 0,
      "priceChangedAt": null,
      "hidden": 0,
      "created_at": "2026-06-25 11:19:45",
      "lastSeen": "2026-07-02T01:08:53.339Z"
    },
    {
      "adID": "1288483403087344",
      "source": "FB",
      "authorUrl": null,
      "author": "Clayton Lacey",
      "postedTime": "2026-06-25T23:05:03.898Z",
      "title": "Atari Hard Drivin upright project working needs cabinet repair no trades",
      "description": "This is a project I am willing to pass on to anyone who wants to restore it. Monitor chassis recapped the tube is original with burn in on screen text and gauges only the text is noticeable during gameplay. The bad the base of the seat and cabinet need repaired or replacing so listing as a project that works and plays the switch on third gear is flaky so currently disabled in settings. No back door or monitor door on the top. No trades.",
      "price": "$500",
      "lat": 33.2442813,
      "lon": -86.8163773,
      "location": "ALABASTER, AL",
      "imageUrl": "https://scontent-dfw6-1.xx.fbcdn.net/v/t39.30808-6/729964610_27722897317303315_769344303372621387_n.jpg?stp=dst-jpg_tt6&cstp=mx1537x2048&ctp=s590x590&_nc_cat=102&ccb=1-7&_nc_sid=aa7b47&_nc_ohc=IlbgpjXZlqsQ7kNvwHJfZeL&_nc_oc=AdpP2djB_1tDNRAvIADxk2UFjdChpUfhk9E2tT3B1DTdvS_oKJQs-95H_wy-jd9IAGs&_nc_zt=23&_nc_ht=scontent-dfw6-1.xx&_nc_gid=LkagGL5mOkm32b8g7LbMyg&_nc_ss=7b2a8&oh=00_AQBD43lqTckjwp4AKAsr6_3rRUhSbzY4EriYp8-7LrJKAA&oe=6A4B8281",
      "adUrl": "https://www.facebook.com/commerce/listing/1288483403087344/",
      "priceChanged": 0,
      "priceChangedAt": null,
      "hidden": 0,
      "created_at": "2026-06-25 11:18:09",
      "lastSeen": "2026-07-02T01:05:03.380Z"
    }
  ]
}